troptumps/__init__.py
troptumps/__main__.py
troptumps/fetch.py
troptumps/pdf.py
troptumps/fonts/DejaVuSans-Bold.ttf
troptumps/fonts/DejaVuSans-BoldOblique.ttf
troptumps/fonts/DejaVuSans-License.txt
troptumps/fonts/DejaVuSans-Oblique.ttf
troptumps/fonts/DejaVuSans.ttf
troptumps/fonts/FreeSerif-License.txt
troptumps/fonts/FreeSerif.ttf
troptumps/fonts/KaiGenGothicCN-License.txt
troptumps/fonts/KaiGenGothicCN.ttf
troptumps-1.0.2.dist-info/LICENSE.txt
troptumps-1.0.2.dist-info/METADATA
troptumps-1.0.2.dist-info/WHEEL
troptumps-1.0.2.dist-info/entry_points.txt
troptumps-1.0.2.dist-info/top_level.txt
troptumps-1.0.2.dist-info/RECORD
