Metadata-Version: 2.1
Name: troptumps
Version: 1.0.2
Summary: A statistics-duelling deck generator using data from wikipedia
Home-page: https://github.com/frimkron/troptumps
Author: Mark Frimston
Author-email: mark@markfrimston.co.uk
License: GPL3
Platform: UNKNOWN
Requires-Python: >=3.6
License-File: LICENSE.txt
Requires-Dist: python-dateutil (>=2.6.0)
Requires-Dist: reportlab (>=3.4.0)
Requires-Dist: pillow (>=1.1.7)
